<enero>Piña:Manzana:Limón:Naranja:Mandarina:Pomelo:Pera:Pera de agua:Chirimoya:Plátano:Uva:Castaña</enero>
<febrero> Piña:Manzana:Pera:Pera de agua:Chirimoya:Naranja:Limón:Pomelo:Plátano:Almendras:Nuez</febrero>
<marzo>Piña:Manzana:Pera:Pera de agua:Limón:Naranja:Pomelo:Plátano:Fresa:Fresón</marzo>
<abril>:Piña:Manzana:Pera:Pera de agua:Limón:Naranja:Pomelo:Plátano:Fresa:Fresón</abril>
<mayor>Piña:Manzana:Pera:Pera de agua:Limón:Naranja:Pomelo:Plátano:Sandía:Albaricoque:Cereza:Melecotón:Ciruela:Níspero:Fresa:Fresón:Grosella:Frambuesa:Breva</mayor>
<junio>Piña:Manzana:Pera:Sandía:Melón:Albaricoque:Cereza:Paraguaya:Melocotón:Ciruela:Níspero:Fresa:Fresón:Grosella:Frambuesa:Anóncubano:Breva:Plátano</junio>
<julio>Piña:Manzana:Limón:Naranja:Pomelo:Pera:Pera de San Juan:Pera duquesa:Sandía:Melon:Uva:Paraguaya:Melocotón:Ciruela:Higo:Plátano</julio>
<agosto>Piña:Manzana:Limón:Pomelo:Pera de agua:Pera:Pera duquesa:Sandia:Melón:Uva:Melocotón:Ciruela:Higo:Plátano</agosto>
<setiembre>Piña:Manzana:Pera de agua:Pera:Pera duquesa:Limón:Naranja:Pomelo:Melón:Uva:Melocotón:Ciruela:Higo:Plátano</setiembre>
<octubre>Piña:Manzana:Pera de agua:Pera:Limón:Naranja:Pomelo:Melón:Uva:Ciruela:Chirimoya:Plátano:Membrillo</octubre>
<noviembre>Piña:Manzana:Pera de agua:Pera:Limón:Naranja:Pomelo:Mandarina:Melón:Uva:Chirimoya:Plátano:Membrillo:Castaña</noviembre>
<diciembre>Piña:Manzana:Pera:Pera de agua:Plátano:Limón:Naranja:Pomelo:Lima:Mandarina:Uva:Chirimoya:Castaña:Almendra:Nuez</diciembre>

